libOPERA_Py/__init__.py
libOPERA_Py/libOPERA_Py.ctf
pyopera/__init__.py
pyopera/opera/__init__.py
pyopera/opera/helpers/opera_helpers.py
pyopera/opera/opera.py
pyopera-0.2.0.dist-info/WHEEL
pyopera-0.2.0.dist-info/METADATA
pyopera-0.2.0.dist-info/LICENSE
pyopera-0.2.0.dist-info/RECORD
