Metadata-Version: 2.1
Name: pyopera
Version: 0.2.0
Summary: The NIH OPERA suite of models with Python specific functionality
License: MIT
Author: Manuel Cabrera
Author-email: cabrera.manuel555@gmail.com
Requires-Python: >=3.8,<4.0
Classifier: License :: OSI Approved :: MIT License
Classifier: Programming Language :: Python :: 3
Classifier: Programming Language :: Python :: 3.8
Classifier: Programming Language :: Python :: 3.9
Classifier: Programming Language :: Python :: 3.10
Classifier: Programming Language :: Python :: 3.11
